chinmoysay/__init__.py
chinmoysay/main.py
chinmoysay-1.1.1.dist-info/METADATA
chinmoysay-1.1.1.dist-info/WHEEL
chinmoysay-1.1.1.dist-info/entry_points.txt
chinmoysay-1.1.1.dist-info/licenses/LICENSE
chinmoysay-1.1.1.dist-info/RECORD
