Metadata-Version: 2.4
Name: chinmoysay
Version: 1.1.1
Summary: A simple CLI greeting application
Project-URL: Homepage, https://github.com/thegreekgoat98/chinmoysay
Project-URL: Repository, https://github.com/thegreekgoat98/chinmoysay
Project-URL: Bug Tracker, https://github.com/thegreekgoat98/chinmoysay/issues
Author-email: Chinmoy Ranjan <ranjanchinmoy@gmail.com>
Maintainer-email: Chinmoy Ranjan <ranjanchinmoy@gmail.com>
License: This project is licensed under the MIT License - see the LICENSE file for details.
License-File: LICENSE
Keywords: cli,command-line,greeting,terminal
Classifier: Development Status :: 5 - Production/Stable
Classifier: Environment :: Console
Classifier: Intended Audience :: End Users/Desktop
Classifier: License :: OSI Approved :: MIT License
Classifier: Programming Language :: Python :: 3
Classifier: Programming Language :: Python :: 3.8
Classifier: Programming Language :: Python :: 3.9
Classifier: Programming Language :: Python :: 3.10
Classifier: Programming Language :: Python :: 3.11
Classifier: Programming Language :: Python :: 3.12
Classifier: Topic :: Utilities
Requires-Python: >=3.8
Requires-Dist: typer>=0.9.0
Provides-Extra: dev
Requires-Dist: black; extra == 'dev'
Requires-Dist: flake8; extra == 'dev'
Requires-Dist: mypy; extra == 'dev'
Requires-Dist: pytest; extra == 'dev'
